bouncing/__init__.py
bouncing/register/__init__.py
bouncing/slider/__init__.py
bouncing/utils/__init__.py
bouncing/utils/cache.py
bouncing/utils/image_tools.py
bouncing/utils/load_image.py
bouncing-1.0.3.dist-info/METADATA
bouncing-1.0.3.dist-info/WHEEL
bouncing-1.0.3.dist-info/top_level.txt
bouncing-1.0.3.dist-info/RECORD
