Metadata-Version: 2.1
Name: bouncing
Version: 1.0.3
Summary: Verification code image recognition!
Home-page: https://github.com/jaygarage/bouncing
Author: Jay
Classifier: Programming Language :: Python :: 3
Classifier: License :: OSI Approved :: MIT License
Classifier: Operating System :: OS Independent
Requires-Python: >=3.7
Requires-Dist: opencv-python
Requires-Dist: xxhash
Requires-Dist: cachetools
Requires-Dist: numpy
Requires-Dist: scikit-image
Requires-Dist: requests
Requires-Dist: fake-useragent
